fastapi_sql_profiler/__init__.py
fastapi_sql_profiler/add_request.py
fastapi_sql_profiler/database.py
fastapi_sql_profiler/middleware.py
fastapi_sql_profiler/models.py
fastapi_sql_profiler/templates/base.html
fastapi_sql_profiler/templates/request.html
fastapi_sql_profiler/templates/request_show.html
fastapi_sql_profiler/templates/sql_query.html
fastapi_sql_profiler/templates/sql_query_detail.html
fastapi_sql_profiler-5.0.0.dist-info/METADATA
fastapi_sql_profiler-5.0.0.dist-info/WHEEL
fastapi_sql_profiler-5.0.0.dist-info/top_level.txt
fastapi_sql_profiler-5.0.0.dist-info/RECORD
