Metadata-Version: 2.1
Name: fastapi-sql-profiler
Version: 5.0.0
Summary: Middleware for profiling and logging database queries in a Python web application
Home-page: https://github.com/Sarvadhi-Solutions/fastapi-sql-profiler.git
Author: Ganesh Sali
Author-email: ganesh@sarvadhi.com
Classifier: Development Status :: 5 - Production/Stable
Classifier: Environment :: Console
Classifier: Environment :: Web Environment
Classifier: Intended Audience :: Developers
Classifier: Operating System :: MacOS :: MacOS X
Classifier: Programming Language :: Python
Classifier: Topic :: Software Development :: Bug Tracking
Requires-Dist: fastapi (>=0.97.0)
Requires-Dist: SQLAlchemy (>=2.0.16)
Requires-Dist: python-dotenv (>=1.0.0)
Requires-Dist: Jinja2 (>=3.1.2)
Requires-Dist: python-multipart (>=0.0.6)
